urbanpy/__init__.py
urbanpy/result.py
urbanpy/urban.py
urbanpython/__init__.py
urbanpython/result.py
urbanpython/urban.py
urbanpython-1.0.4.dist-info/METADATA
urbanpython-1.0.4.dist-info/WHEEL
urbanpython-1.0.4.dist-info/top_level.txt
urbanpython-1.0.4.dist-info/RECORD
