Metadata-Version: 2.1
Name: urbanpython
Version: 1.0.4
Summary: urbanpython is an API wrapper for the Urban Dictionary JSON API
Home-page: https://github.com/MakufonSkifto/urbanpy
Author: MakufonSkifto
License: MIT
Platform: UNKNOWN
Classifier: Programming Language :: Python :: 3
Classifier: License :: OSI Approved :: MIT License
Requires-Python: >=3.6
Requires-Dist: requests
